pkg_updater/__init__.py
pkg_updater/app.py
pkg_updater/favicon.svg
pkg_updater/handlers.py
pkg_updater/logger.py
pkg_updater/py.typed
pkg_updater/startup.py
pkg_updater/updater.py
pkg_updater-1.0.6.dist-info/licenses/LICENSE
pkg_updater-1.0.6.dist-info/METADATA
pkg_updater-1.0.6.dist-info/WHEEL
pkg_updater-1.0.6.dist-info/entry_points.txt
pkg_updater-1.0.6.dist-info/top_level.txt
pkg_updater-1.0.6.dist-info/RECORD
