Metadata-Version: 2.4
Name: pkg-updater
Version: 1.0.6
Summary: A python script to update packages
Author-email: Pradish Bijukchhe <pradishbijukchhe@gmail.com>
License: Copyright (c) 2018 The Python Packaging Authority
Project-URL: Homepage, https://github.com/sandbox-pokhara/pkg-updater
Project-URL: Issues, https://github.com/sandbox-pokhara/pkg-updater/issues
Classifier: Programming Language :: Python :: 3
Requires-Python: >=3
License-File: LICENSE
Requires-Dist: PyQt6==6.5.3
Requires-Dist: PyQt6-Qt6==6.5.3
Requires-Dist: PyQt6-sip==13.6.0
Dynamic: license-file
